libfpga/__init__.py
libfpga/mpsoc.py
libfpga/xdma.py
libfpga-0.0.13.dist-info/LICENSE
libfpga-0.0.13.dist-info/METADATA
libfpga-0.0.13.dist-info/WHEEL
libfpga-0.0.13.dist-info/top_level.txt
libfpga-0.0.13.dist-info/RECORD
