Metadata-Version: 2.1
Name: libfpga
Version: 0.0.13
Summary: Python3 library for operating DMA and register manipualtion on Xilinx FPGAs
Home-page: https://github.com/QianfengClarkShen/libfpga
Author: Qianfeng (Clark) Shen
Author-email: qianfeng.shen@gmail.com
License: UNKNOWN
Platform: UNKNOWN
Classifier: Programming Language :: Python :: 3
Classifier: License :: OSI Approved :: MIT License
Classifier: Operating System :: POSIX :: Linux
Requires-Python: >=3.5.0
